felicidad/__init__.py
felicidad/cli.py
felicidad/core.py
felicidad-1.0.0.dist-info/licenses/LICENSE
felicidad-1.0.0.dist-info/METADATA
felicidad-1.0.0.dist-info/WHEEL
felicidad-1.0.0.dist-info/entry_points.txt
felicidad-1.0.0.dist-info/top_level.txt
felicidad-1.0.0.dist-info/RECORD
