Metadata-Version: 2.4
Name: felicidad
Version: 1.0.0
Summary: Tu dosis diaria de felicidad programática 💖
Home-page: https://github.com/XzLuizem/felicidad
Author: XzLuizem
Author-email:  luism.jim7@gmail.com
Project-URL: Bug Reports, https://github.com/XzLuizem/felicidad/issues
Project-URL: Source, https://github.com/XzLuizem/felicidad
Keywords: happiness,wellbeing,mental-health,developer-tools,fun
Classifier: Development Status :: 4 - Beta
Classifier: Intended Audience :: Developers
Classifier: Topic :: Software Development :: Libraries :: Python Modules
Classifier: License :: OSI Approved :: MIT License
Classifier: Programming Language :: Python :: 3
Classifier: Programming Language :: Python :: 3.9
Classifier: Programming Language :: Python :: 3.10
Classifier: Programming Language :: Python :: 3.11
Classifier: Programming Language :: Python :: 3.12
Classifier: Programming Language :: Python :: 3.13
Classifier: Programming Language :: Python :: 3.14
Classifier: Operating System :: OS Independent
Requires-Python: >=3.7
License-File: LICENSE
Dynamic: author
Dynamic: author-email
Dynamic: classifier
Dynamic: description
Dynamic: description-content-type
Dynamic: home-page
Dynamic: keywords
Dynamic: license-file
Dynamic: project-url
Dynamic: requires-python
Dynamic: summary
